setup.py
hieratic/__init__.py
hieratic/collection.py
hieratic/exceptions.py
hieratic/index.py
hieratic/item.py
hieratic/service.py
hieratic.egg-info/PKG-INFO
hieratic.egg-info/SOURCES.txt
hieratic.egg-info/dependency_links.txt
hieratic.egg-info/entry_points.txt
hieratic.egg-info/requires.txt
hieratic.egg-info/top_level.txt
hieratic/engine/__init__.py
hieratic/engine/memory.py