Metadata-Version: 1.1
Name: hieratic
Version: 0.0.4
Summary: hierarchical resource implementation.
Home-page: https://github.com/succhiello/hieratic
Author: Satoshi Ebihara
Author-email: succhiello@gmail.com
License: MIT
Platform: UNKNOWN
Classifier: Development Status :: 3 - Alpha
Classifier: Environment :: Web Environment
Classifier: Intended Audience :: Developers
Classifier: License :: OSI Approved :: MIT License
Classifier: Operating System :: POSIX :: Linux
Classifier: Programming Language :: Python
